{
  "sorted_middleware": [],
  "middleware": {
    "/": {
      "files": [
        "server/edge/chunks/_c998e4ec._.js",
        "server/edge/chunks/[root-of-the-server]__3ae1ca41._.js",
        "server/edge/chunks/edge-wrapper_5ceeb5e6.js"
      ],
      "name": "middleware",
      "page": "/",
      "matchers": [
        {
          "regexp": "/:nextData(_next/data/[^/]{1,})?/((?!_next/static|_next/image|favicon.ico|robots.txt|sitemap.xml|api/auth).*){(\\\\.json)}?",
          "originalSource": "/((?!_next/static|_next/image|favicon.ico|robots.txt|sitemap.xml|api/auth).*)"
        }
      ],
      "wasm": [],
      "assets": [],
      "env": {
        "__NEXT_BUILD_ID": "development",
        "NEXT_SERVER_ACTIONS_ENCRYPTION_KEY": "WmsXonVKTSIlxZWCzB2LGs3bwSM/vHrKKn1eEcCwaIE=",
        "__NEXT_PREVIEW_MODE_ID": "f1292fe2b3d904124ff1b596827c3535",
        "__NEXT_PREVIEW_MODE_ENCRYPTION_KEY": "eed8f6b3799e52d4c260f02a66c58638d5cba3e94e4ef60adf9bd3690e92d49a",
        "__NEXT_PREVIEW_MODE_SIGNING_KEY": "d34deb345c27de482b9547d69e1655d3d406ab17e44928c9dfd7788120c29d4e"
      }
    }
  },
  "instrumentation": null,
  "functions": {}
}