{
  "sorted_middleware": [],
  "middleware": {
    "/": {
      "files": [
        "server/edge/chunks/_c27050e7._.js",
        "server/edge/chunks/[root-of-the-server]__3ae1ca41._.js",
        "server/edge/chunks/edge-wrapper_e9d5013e.js"
      ],
      "name": "middleware",
      "page": "/",
      "matchers": [
        {
          "regexp": "/:nextData(_next/data/[^/]{1,})?/((?!_next/static|_next/image|favicon.ico|sitemap.xml|robots.txt|api/auth).*){(\\\\.json)}?",
          "originalSource": "/((?!_next/static|_next/image|favicon.ico|sitemap.xml|robots.txt|api/auth).*)"
        }
      ],
      "wasm": [],
      "assets": [],
      "env": {
        "__NEXT_BUILD_ID": "development",
        "NEXT_SERVER_ACTIONS_ENCRYPTION_KEY": "7B0jrHMbYAoFxlq9Ka2jYUrz5Od+rYOM5CcdA68HsN4=",
        "__NEXT_PREVIEW_MODE_ID": "c041e2f93189478f3c062db2afec8d91",
        "__NEXT_PREVIEW_MODE_ENCRYPTION_KEY": "96bfdd9d2d287c48aed8db338cd32bddaa013df19cdf43152b9b86381a6bb29b",
        "__NEXT_PREVIEW_MODE_SIGNING_KEY": "08a10bb96a60d964c85c089354d9950e0115600bf7d724c32e1d59d39770ba2e"
      }
    }
  },
  "instrumentation": null,
  "functions": {}
}